aioconnection/__init__.py
aioconnection/protocol.py
aioconnection/utils.py
aioconnection/transport/__init__.py
aioconnection/transport/serialport/__init__.py
aioconnection/transport/serialport/core.py
aioconnection/transport/serialport/transport.py
aioconnection-0.1.3.dist-info/LICENSE
aioconnection-0.1.3.dist-info/METADATA
aioconnection-0.1.3.dist-info/WHEEL
aioconnection-0.1.3.dist-info/top_level.txt
aioconnection-0.1.3.dist-info/RECORD
