Metadata-Version: 2.1
Name: aioconnection
Version: 0.1.3
Summary: Async messaging
Home-page: https://github.com/means0nothing/AioConnection
Author: Pavel Shevcov
Author-email: means0nothing@gmail.com
License: MIT
Classifier: Development Status :: 3 - Alpha
Classifier: Intended Audience :: Developers
Classifier: License :: OSI Approved :: MIT License
Classifier: Operating System :: Microsoft :: Windows :: Windows 10
Classifier: Programming Language :: Python :: 3.9
Classifier: Programming Language :: Python :: 3.10
Classifier: Topic :: Software Development :: Libraries :: Python Modules
Requires-Python: >=3.9
License-File: LICENSE
Requires-Dist: pyserial (==3.5)
Requires-Dist: notool (==0.1.2)
